afmaths/__init__.py
afmaths/afmaths.py
afmaths/cs.py
afmaths/formula.py
afmaths/graph.py
afmaths/list.py
afmaths/physics.py
afmaths-1.0.3.dist-info/LICENSE
afmaths-1.0.3.dist-info/METADATA
afmaths-1.0.3.dist-info/WHEEL
afmaths-1.0.3.dist-info/top_level.txt
afmaths-1.0.3.dist-info/RECORD
