Metadata-Version: 2.1
Name: afmaths
Version: 1.0.3
Summary: A suite of mathematical functions with outputs to help revise math
Author-email: Artúr Foden <fodena@tcd.ie>
License: MIT License
Project-URL: Homepage, https://github.com/Arturius771/afmaths/
Project-URL: Issues, https://github.com/Arturius771/afmaths/issues
Classifier: Programming Language :: Python :: 3
Classifier: License :: OSI Approved :: MIT License
Classifier: Operating System :: OS Independent
Requires-Python: >=3.7
License-File: LICENSE
